filepreviews/__init__.py
filepreviews/__main__.py
filepreviews/api.py
filepreviews/client.py
filepreviews/exceptions.py
filepreviews/models.py
filepreviews/session.py
filepreviews-2.0.2.dist-info/DESCRIPTION.rst
filepreviews-2.0.2.dist-info/entry_points.txt
filepreviews-2.0.2.dist-info/METADATA
filepreviews-2.0.2.dist-info/metadata.json
filepreviews-2.0.2.dist-info/RECORD
filepreviews-2.0.2.dist-info/top_level.txt
filepreviews-2.0.2.dist-info/WHEEL
