Metadata-Version: 2.0
Name: filepreviews
Version: 2.0.2
Summary: Python client library and CLI tool for FilePreviews.io
Home-page: https://github.com/GetBlimp/filepreviews-python
Author: José Padilla
Author-email: jpadilla@blimp.io
License: MIT
Keywords: file previews thumbnails metadata exif ocr
Platform: UNKNOWN
Classifier: Development Status :: 5 - Production/Stable
Classifier: License :: OSI Approved :: MIT License
Classifier: Intended Audience :: Developers
Classifier: Operating System :: OS Independent
Classifier: Programming Language :: Python
Classifier: Programming Language :: Python :: 2.7
Classifier: Programming Language :: Python :: 3.2
Classifier: Programming Language :: Python :: 3.3
Classifier: Programming Language :: Python :: 3.4
Classifier: Topic :: Utilities
Requires-Dist: requests (>=2.7.0,<3.0.0)
Requires-Dist: click (>=4.0,<5.0)
